README.md
setup.py
exsimple/__init__.py
exsimple/exsimple.py
exsimple.egg-info/PKG-INFO
exsimple.egg-info/SOURCES.txt
exsimple.egg-info/dependency_links.txt
exsimple.egg-info/entry_points.txt
exsimple.egg-info/top_level.txt