Metadata-Version: 1.1
Name: exsimple
Version: 1.0.3
Summary: A public, open, share net-disc.
Home-page: https://github.com/XenoAmess/EXsimple
Author: XenoAmess
Author-email: xenoamess@gmail.com
License: https://github.com/XenoAmess/EXsimple/blob/master/LICENCE
Platform: UNKNOWN
Classifier: Programming Language :: Python :: 3
Classifier: Programming Language :: Python :: 3.3
Classifier: Programming Language :: Python :: 3.4
Classifier: Programming Language :: Python :: 3.5
Classifier: Programming Language :: Python :: 3.6
Classifier: Programming Language :: Python :: 3.7
